setup.cfg
setup.py
buildok/__init__.py
buildok/__main__.py
buildok/action.py
buildok/bootstrap.py
buildok/converter.py
buildok/matcher.py
buildok/parser.py
buildok/placeholder.py
buildok/reader.py
buildok/report.py
buildok/script.py
buildok/statement.py
buildok/version.py
buildok.egg-info/PKG-INFO
buildok.egg-info/SOURCES.txt
buildok.egg-info/dependency_links.txt
buildok.egg-info/entry_points.txt
buildok.egg-info/top_level.txt
buildok/converters/__init__.py
buildok/converters/bash.py
buildok/readers/__init__.py
buildok/readers/read_me.py
buildok/statements/__init__.py
buildok/statements/chdir.py
buildok/statements/chmod.py
buildok/statements/chown.py
buildok/statements/copy.py
buildok/statements/duckduckgo.py
buildok/statements/edit_file.py
buildok/statements/github_search.py
buildok/statements/google.py
buildok/statements/install.py
buildok/statements/install_npm.py
buildok/statements/install_pip.py
buildok/statements/invoke.py
buildok/statements/kill.py
buildok/statements/listdir.py
buildok/statements/mkdir.py
buildok/statements/move.py
buildok/statements/noop.py
buildok/statements/reinstall.py
buildok/statements/remove.py
buildok/statements/service_disable.py
buildok/statements/service_enable.py
buildok/statements/service_reload.py
buildok/statements/service_restart.py
buildok/statements/service_start.py
buildok/statements/service_status.py
buildok/statements/service_stop.py
buildok/statements/shell.py
buildok/statements/symlink.py
buildok/statements/touch.py
buildok/statements/uninstall.py
buildok/statements/web.py
buildok/statements/wikipedia.py
buildok/structures/__init__.py
buildok/structures/guide.py
buildok/structures/instruction.py
buildok/structures/topic.py
buildok/util/__init__.py
buildok/util/analyze.py
buildok/util/console.py
buildok/util/locker.py
buildok/util/log.py
buildok/util/lookup.py
buildok/util/readerr.py
buildok/util/shell.py
buildok/util/sysenv.py
test/tester.py