Metadata-Version: 1.1
Name: buildok
Version: 0.4.1
Summary: A tool to automate build steps from README files.
Home-page: https://github.com/lexndru/buildok
Author: Alexandru Catrina
Author-email: alex@codeissues.net
License: MIT
Download-URL: https://github.com/lexndru/buildok/archive/v0.4.1.tar.gz
Keywords: build-tool,build-automation,readme,buildok
Platform: UNKNOWN
Classifier: Development Status :: 4 - Beta
Classifier: Intended Audience :: Developers
Classifier: Intended Audience :: End Users/Desktop
Classifier: Topic :: Software Development :: Build Tools
Classifier: License :: OSI Approved :: MIT License
Classifier: Programming Language :: Python :: 2.7
